vhdl_ls/__init__.py
vhdl_ls/vhdl_ls.py
SimplHDL_vhdl_ls-0.1.dist-info/LICENSE
SimplHDL_vhdl_ls-0.1.dist-info/METADATA
SimplHDL_vhdl_ls-0.1.dist-info/WHEEL
SimplHDL_vhdl_ls-0.1.dist-info/entry_points.txt
SimplHDL_vhdl_ls-0.1.dist-info/top_level.txt
SimplHDL_vhdl_ls-0.1.dist-info/RECORD
