Metadata-Version: 2.1
Name: SimplHDL-vhdl_ls
Version: 0.1
Summary: Generate VHDL_LS configuration from SimplHDL project.
Author-email: Troels Folke <troelsmf@gmail.com>
License: MIT License
Project-URL: Homepage, https://github.com/Toucanfan/SimplHDL-vhdl_ls
Project-URL: Bug Tracker, https://github.com/Toucanfan/SimplHDL-vhdl_ls/issues
Classifier: Programming Language :: Python :: 3
Classifier: License :: OSI Approved :: MIT License
Classifier: Operating System :: OS Independent
License-File: LICENSE
Requires-Dist: SimplHDL
Requires-Dist: Jinja2
